RobotRetrier/RobotRetrier.py
RobotRetrier/__init__.py
RobotRetrier/core.py
RobotRetrier/event_logger.py
RobotRetrier/execution_tree_view.py
RobotRetrier/gui.py
robot_retrier-1.5.0.dist-info/METADATA
robot_retrier-1.5.0.dist-info/WHEEL
robot_retrier-1.5.0.dist-info/entry_points.txt
robot_retrier-1.5.0.dist-info/top_level.txt
robot_retrier-1.5.0.dist-info/RECORD
